qinling_dashboard/__init__.py
qinling_dashboard/exceptions.py
qinling_dashboard/utils.py
qinling_dashboard/validators.py
qinling_dashboard/api/__init__.py
qinling_dashboard/api/qinling.py
qinling_dashboard/conf/qinling_policy.json
qinling_dashboard/content/__init__.py
qinling_dashboard/content/executions/__init__.py
qinling_dashboard/content/executions/forms.py
qinling_dashboard/content/executions/panel.py
qinling_dashboard/content/executions/tables.py
qinling_dashboard/content/executions/tabs.py
qinling_dashboard/content/executions/urls.py
qinling_dashboard/content/executions/views.py
qinling_dashboard/content/executions/templates/executions/_create.html
qinling_dashboard/content/executions/templates/executions/_detail_logs.html
qinling_dashboard/content/executions/templates/executions/_detail_overview.html
qinling_dashboard/content/executions/templates/executions/_execution_result.html
qinling_dashboard/content/executions/templates/executions/create.html
qinling_dashboard/content/executions/templates/executions/detail.html
qinling_dashboard/content/functions/__init__.py
qinling_dashboard/content/functions/forms.py
qinling_dashboard/content/functions/panel.py
qinling_dashboard/content/functions/tables.py
qinling_dashboard/content/functions/tabs.py
qinling_dashboard/content/functions/urls.py
qinling_dashboard/content/functions/views.py
qinling_dashboard/content/functions/templates/functions/_create_function.html
qinling_dashboard/content/functions/templates/functions/_create_version.html
qinling_dashboard/content/functions/templates/functions/_detail_executions.html
qinling_dashboard/content/functions/templates/functions/_detail_overview.html
qinling_dashboard/content/functions/templates/functions/_detail_version_overview.html
qinling_dashboard/content/functions/templates/functions/_detail_versions.html
qinling_dashboard/content/functions/templates/functions/_update_function.html
qinling_dashboard-4.0.0.dist-info/DESCRIPTION.rst
qinling_dashboard-4.0.0.dist-info/METADATA
qinling_dashboard-4.0.0.dist-info/RECORD
qinling_dashboard-4.0.0.dist-info/WHEEL
qinling_dashboard-4.0.0.dist-info/metadata.json
qinling_dashboard-4.0.0.dist-info/pbr.json
qinling_dashboard-4.0.0.dist-info/top_level.txt
