Metadata-Version: 2.0
Name: qinling-dashboard
Version: 4.0.0
Summary: Qinling Management Dashboard
Home-page: https://docs.openstack.org/qinling-dashboard/latest/
Author: OpenStack
Author-email: openstack-discuss@lists.openstack.org
License: UNKNOWN
Platform: UNKNOWN
Classifier: Environment :: OpenStack
Classifier: Intended Audience :: Information Technology
Classifier: Intended Audience :: System Administrators
Classifier: License :: OSI Approved :: Apache Software License
Classifier: Operating System :: POSIX :: Linux
Classifier: Programming Language :: Python
Classifier: Programming Language :: Python :: Implementation :: CPython
Classifier: Programming Language :: Python :: 3 :: Only
Classifier: Programming Language :: Python :: 3
Classifier: Programming Language :: Python :: 3.6
Classifier: Programming Language :: Python :: 3.7
Requires-Python: >=3.6
Requires-Dist: horizon (>=17.1.0)
Requires-Dist: pbr (!=2.1.0,>=2.0.0)
Requires-Dist: python-qinlingclient (>=1.1.0)
